ShiyanlouWebJiaochengHeji20160904Fix1/README.md
ShiyanlouWebJiaochengHeji20160904Fix1/__init__.py
ShiyanlouWebJiaochengHeji20160904Fix1/__main__.py
ShiyanlouWebJiaochengHeji20160904Fix1/file.epub
ShiyanlouWebJiaochengHeji20160904Fix1/index.html
ShiyanlouWebJiaochengHeji20160904Fix1/css/__init__.py
ShiyanlouWebJiaochengHeji20160904Fix1/css/annotations.css
ShiyanlouWebJiaochengHeji20160904Fix1/css/main.css
ShiyanlouWebJiaochengHeji20160904Fix1/css/normalize.css
ShiyanlouWebJiaochengHeji20160904Fix1/css/popup.css
ShiyanlouWebJiaochengHeji20160904Fix1/font/__init__.py
ShiyanlouWebJiaochengHeji20160904Fix1/font/fontello.eot
ShiyanlouWebJiaochengHeji20160904Fix1/font/fontello.svg
ShiyanlouWebJiaochengHeji20160904Fix1/font/fontello.ttf
ShiyanlouWebJiaochengHeji20160904Fix1/font/fontello.woff
ShiyanlouWebJiaochengHeji20160904Fix1/img/__init__.py
ShiyanlouWebJiaochengHeji20160904Fix1/img/annotator-glyph-sprite.png
ShiyanlouWebJiaochengHeji20160904Fix1/img/annotator-icon-sprite.png
ShiyanlouWebJiaochengHeji20160904Fix1/img/apple-touch-icon.png
ShiyanlouWebJiaochengHeji20160904Fix1/img/cancelfullscreen.png
ShiyanlouWebJiaochengHeji20160904Fix1/img/close.png
ShiyanlouWebJiaochengHeji20160904Fix1/img/fullscreen.png
ShiyanlouWebJiaochengHeji20160904Fix1/img/loader.gif
ShiyanlouWebJiaochengHeji20160904Fix1/img/menu-icon.png
ShiyanlouWebJiaochengHeji20160904Fix1/img/save.png
ShiyanlouWebJiaochengHeji20160904Fix1/img/saved.png
ShiyanlouWebJiaochengHeji20160904Fix1/img/settings-s.png
ShiyanlouWebJiaochengHeji20160904Fix1/img/settings.png
ShiyanlouWebJiaochengHeji20160904Fix1/img/star.png
ShiyanlouWebJiaochengHeji20160904Fix1/js/__init__.py
ShiyanlouWebJiaochengHeji20160904Fix1/js/epub.js
ShiyanlouWebJiaochengHeji20160904Fix1/js/epub.min.js
ShiyanlouWebJiaochengHeji20160904Fix1/js/epub.min.map
ShiyanlouWebJiaochengHeji20160904Fix1/js/hooks.min.js
ShiyanlouWebJiaochengHeji20160904Fix1/js/hooks.min.map
ShiyanlouWebJiaochengHeji20160904Fix1/js/reader.js
shiyanlou_web_jiaocheng_heji_20160904_fix1-2024.3.2.0.dist-info/METADATA
shiyanlou_web_jiaocheng_heji_20160904_fix1-2024.3.2.0.dist-info/WHEEL
shiyanlou_web_jiaocheng_heji_20160904_fix1-2024.3.2.0.dist-info/entry_points.txt
shiyanlou_web_jiaocheng_heji_20160904_fix1-2024.3.2.0.dist-info/top_level.txt
shiyanlou_web_jiaocheng_heji_20160904_fix1-2024.3.2.0.dist-info/RECORD
